sphinx_minipres/__init__.py
sphinx_minipres/_version.py
sphinx_minipres/_static/minipres.js
sphinx_minipres-0.2.1.dist-info/METADATA
sphinx_minipres-0.2.1.dist-info/WHEEL
sphinx_minipres-0.2.1.dist-info/top_level.txt
sphinx_minipres-0.2.1.dist-info/RECORD
