Metadata-Version: 2.1
Name: sphinx-minipres
Version: 0.2.1
Summary: Sphinx extension to turn any web page into a lightweight presentation
Home-page: https://github.com/coderefinery/sphinx-minipres
Author: Richard Darst
Author-email: UNKNOWN
License: UNKNOWN
Keywords: sphinx-extension
Platform: UNKNOWN
Classifier: Programming Language :: Python :: 3
Classifier: License :: OSI Approved :: MIT License
Classifier: Operating System :: OS Independent
Classifier: Development Status :: 4 - Beta
Classifier: Framework :: Sphinx
Classifier: Framework :: Sphinx :: Extension
